htmgem/__init__.py
htmgem/doc.py
htmgem/tags.py
htmgem/resources/__init__.py
htmgem-0.0.2.dist-info/METADATA
htmgem-0.0.2.dist-info/WHEEL
htmgem-0.0.2.dist-info/top_level.txt
htmgem-0.0.2.dist-info/RECORD
