Metadata-Version: 2.1
Name: htmgem
Version: 0.0.2
Summary: Generate HTML with Python!
Home-page: https://github.com/ClimenteA/htmgem
Author: Alin Climente
Author-email: climente.alin@gmail.com
License: MIT
Platform: UNKNOWN
Requires-Python: >3.5
